README.txt
setup.py
erajp/__init__.py
erajp/converter.py
erajp.egg-info/PKG-INFO
erajp.egg-info/SOURCES.txt
erajp.egg-info/dependency_links.txt
erajp.egg-info/requires.txt
erajp.egg-info/top_level.txt