Metadata-Version: 1.0
Name: erajp
Version: 0.0.4
Summary: Convert datetime to Japanese era
Home-page: https://github.com/recruit-mtl/erajp
Author: kasajei
Author-email: kasajei@me.com
License: UNKNOWN
Platform: UNKNOWN
